brawser/main.py
brawser/open_console.py
brawser/version.py
brawser-1.0.2.dist-info/LICENSE
brawser-1.0.2.dist-info/METADATA
brawser-1.0.2.dist-info/WHEEL
brawser-1.0.2.dist-info/entry_points.txt
brawser-1.0.2.dist-info/top_level.txt
brawser-1.0.2.dist-info/RECORD
