Metadata-Version: 2.1
Name: brawser
Version: 1.0.2
Summary: Open browser with Management Console
Author: itsuki
License: MIT
License-File: LICENSE
Requires-Dist: click (>=8.1.3)
Requires-Dist: boto3 (>=1.26.126)
Requires-Dist: requests
